idali/__init__.py
idali/__main__.py
idali_pkg_devjstn-1.0.2.dist-info/LICENSE.txt
idali_pkg_devjstn-1.0.2.dist-info/METADATA
idali_pkg_devjstn-1.0.2.dist-info/WHEEL
idali_pkg_devjstn-1.0.2.dist-info/top_level.txt
idali_pkg_devjstn-1.0.2.dist-info/RECORD
