Metadata-Version: 2.1
Name: idali-pkg-devjstn
Version: 1.0.2
Summary: Automates file creation for web development when starting new projects
Home-page: https://github.com/justinbalaguer/idali
Author: Justin Balaguer
Author-email: justinanthony.primary@gmail.com
License: UNKNOWN
Platform: UNKNOWN
Classifier: Programming Language :: Python :: 3
Classifier: License :: OSI Approved :: MIT License
Classifier: Operating System :: OS Independent
Requires-Python: >=3.6
